{"inkVersion":21,"root":[[{"->":"default"},["done",{"#f":5,"#n":"g-0"}],null],"done",{"default":["^Halo, ","ev",{"VAR?":"player"},"out","/ev","^. Sedang apa kamu?  ","#","^speaker: Jaka","/#","\n","^Ngga ngapa - ngapain.  ","#","^speaker: ","ev",{"VAR?":"player"},"out","/ev","/#","\n","^Apa kamu mau bergabung untuk berlari?  ","#","^speaker: Jaka","/#","\n","^Tidak. Emangnya kamu ngapain lari di lapangan ini?  ","#","^speaker: ","ev",{"VAR?":"player"},"out","/ev","/#","\n","^Aku dihukum karena sengaja coret - coret di tembok. hahaha.  ","#","^speaker: Jaka","/#","\n","^Emang kamu ya bandel wkwkwk.  ","#","^speaker: ","ev",{"VAR?":"player"},"out","/ev","/#","\n","^Jaka lanjut untuk berlari.  ","#","^speaker: narrator","/#","\n","end",{"#f":1}],"global decl":["ev","str","^player","/str",{"VAR=":"player"},"/ev","end",null],"#f":1}],"listDefs":{}}